flask_gen/__init__.py
flask_gen/__main__.py
flask_gen/cli.py
flask_gen/commands.py
flask_gen/src/__init__.py
flask_gen/src/app_creator.py
flask_gen/src/project_creator.py
test/__init__.py
test/test_app_creator.py
test/test_project_creator.py
flask_gen-0.2.0.dist-info/LICENSE
flask_gen-0.2.0.dist-info/METADATA
flask_gen-0.2.0.dist-info/WHEEL
flask_gen-0.2.0.dist-info/entry_points.txt
flask_gen-0.2.0.dist-info/top_level.txt
flask_gen-0.2.0.dist-info/RECORD
