Metadata-Version: 2.2
Name: Flask-gen
Version: 0.2.0
Summary: A command-line tool to generate Flask projects and applications.
Home-page: https://github.com/htshongany/Flask-gen
Author: Tshongani Hamadou
Author-email: sirehtshongany@gmail.com
Classifier: Programming Language :: Python :: 3
Classifier: Framework :: Flask
Classifier: License :: OSI Approved :: MIT License
Classifier: Operating System :: OS Independent
Requires-Python: >=3.7
License-File: LICENSE
Requires-Dist: Flask<3.0.0,>=2.0.0
Requires-Dist: Flask-SQLAlchemy<3.0.0,>=2.5.0
Requires-Dist: Flask-Migrate<4.0.0,>=3.0.0
Requires-Dist: python-dotenv<2.0.0,>=0.15.0
Requires-Dist: SQLAlchemy<2.0,>=1.4
Dynamic: author
Dynamic: author-email
Dynamic: classifier
Dynamic: description
Dynamic: description-content-type
Dynamic: home-page
Dynamic: requires-dist
Dynamic: requires-python
Dynamic: summary
